README.md
setup.py
mitmdump/__init__.py
mitmdump/mitmdump.py
mitmdump.egg-info/PKG-INFO
mitmdump.egg-info/SOURCES.txt
mitmdump.egg-info/dependency_links.txt
mitmdump.egg-info/requires.txt
mitmdump.egg-info/top_level.txt