Metadata-Version: 2.1
Name: mitmdump
Version: 1.1.0
Summary: 以编程的方式运行 mitmproxy
Home-page: https://github.com/mocobk/mitmdump
Author: mocobk
Author-email: mailmzb@qq.com
License: UNKNOWN
Platform: UNKNOWN
Classifier: Programming Language :: Python :: 3 :: Only
Classifier: Programming Language :: Python :: 3.6
Classifier: Programming Language :: Python :: 3.7
Classifier: Programming Language :: Python :: 3.8
Classifier: License :: OSI Approved :: MIT License
Classifier: Operating System :: OS Independent
